setup.py
iqpp/__init__.py
iqpp.plone.commenting.egg-info/PKG-INFO
iqpp.plone.commenting.egg-info/SOURCES.txt
iqpp.plone.commenting.egg-info/dependency_links.txt
iqpp.plone.commenting.egg-info/entry_points.txt
iqpp.plone.commenting.egg-info/namespace_packages.txt
iqpp.plone.commenting.egg-info/not-zip-safe
iqpp.plone.commenting.egg-info/paster_plugins.txt
iqpp.plone.commenting.egg-info/requires.txt
iqpp.plone.commenting.egg-info/top_level.txt
iqpp/plone/__init__.py
iqpp/plone/commenting/README.txt
iqpp/plone/commenting/__init__.py
iqpp/plone/commenting/catalog.py
iqpp/plone/commenting/config.py
iqpp/plone/commenting/configure.zcml
iqpp/plone/commenting/content.py
iqpp/plone/commenting/interfaces.py
iqpp/plone/commenting/overrides.zcml
iqpp/plone/commenting/permissions.zcml
iqpp/plone/commenting/profiles.zcml
iqpp/plone/commenting/setuphandlers.py
iqpp/plone/commenting/subscribers.py
iqpp/plone/commenting/utils.py
iqpp/plone/commenting/version.txt
iqpp/plone/commenting/adapters/__init__.py
iqpp/plone/commenting/adapters/commenting.py
iqpp/plone/commenting/adapters/configure.zcml
iqpp/plone/commenting/adapters/options.py
iqpp/plone/commenting/adapters/transformations.py
iqpp/plone/commenting/browser/__init__.py
iqpp/plone/commenting/browser/comment_form.pt
iqpp/plone/commenting/browser/comment_form.py
iqpp/plone/commenting/browser/configure.zcml
iqpp/plone/commenting/browser/delete_comments.py
iqpp/plone/commenting/browser/manage_comment_form.pt
iqpp/plone/commenting/browser/manage_comment_form.py
iqpp/plone/commenting/browser/my_comments.pt
iqpp/plone/commenting/browser/my_comments.py
iqpp/plone/commenting/browser/options_tab.pt
iqpp/plone/commenting/browser/options_tab.py
iqpp/plone/commenting/browser/preview_comment.pt
iqpp/plone/commenting/browser/preview_comment.py
iqpp/plone/commenting/browser/review_comments.py
iqpp/plone/commenting/controlpanel/__init__.py
iqpp/plone/commenting/controlpanel/commenting.py
iqpp/plone/commenting/controlpanel/configure.zcml
iqpp/plone/commenting/docs/__init__.py
iqpp/plone/commenting/docs/testCommentsView.rst
iqpp/plone/commenting/docs/testWorkflow.rst
iqpp/plone/commenting/portlets/__init__.py
iqpp/plone/commenting/portlets/configure.zcml
iqpp/plone/commenting/portlets/pending_comments.pt
iqpp/plone/commenting/portlets/pending_comments.py
iqpp/plone/commenting/profiles/default/actionicons.xml
