Metadata-Version: 1.0
Name: iqpp.plone.commenting
Version: 0.5.beta.2
Summary: A commenting system for Plone
Home-page: http://iqpp.de
Author: Kai Diefenbach
Author-email: kai.diefenbach@iqpp.de
License: GPL
Platform: UNKNOWN
Classifier: Framework :: Plone
Classifier: Framework :: Zope2
Classifier: Framework :: Zope3
Classifier: Programming Language :: Python
Classifier: Topic :: Software Development :: Libraries :: Python Modules
